perculus_sdk_python/__init__.py
perculus_sdk_python/auth.py
perculus_sdk_python/client.py
perculus_sdk_python/attendee/__init__.py
perculus_sdk_python/attendee/client.py
perculus_sdk_python/session/__init__.py
perculus_sdk_python/session/client.py
perculus_sdk_python/user/__init__.py
perculus_sdk_python/user/client.py
perculus_sdk_python-0.2.2.dist-info/METADATA
perculus_sdk_python-0.2.2.dist-info/WHEEL
perculus_sdk_python-0.2.2.dist-info/top_level.txt
perculus_sdk_python-0.2.2.dist-info/RECORD
