Metadata-Version: 2.1
Name: perculus_sdk_python
Version: 0.2.2
Summary: Perculus Python Software Development Kit
Home-page: https://github.com/perculus/perculus-sdk-python
Author: Perculus Dev Team
Author-email: zafer@perculus.com
Classifier: Programming Language :: Python :: 3
Classifier: License :: OSI Approved :: MIT License
Classifier: Operating System :: OS Independent
Requires-Python: >=3.6
Requires-Dist: python-dotenv==1.0.1
Requires-Dist: requests==2.32.3
Requires-Dist: urllib3==2.2.2
